README
setup.py
distribute_install_component.egg-info/PKG-INFO
distribute_install_component.egg-info/SOURCES.txt
distribute_install_component.egg-info/dependency_links.txt
distribute_install_component.egg-info/entry_points.txt
distribute_install_component.egg-info/top_level.txt
install_component/__init__.py