Metadata-Version: 1.0
Name: distribute-install-component
Version: 0.1
Summary: Distribute extension to install components listed in extras_require
Home-page: https://bitbucket.org/lordmauve/distribute-install_component
Author: Daniel Pope
Author-email: mauve@mauveweb.co.uk
License: UNKNOWN
Platform: UNKNOWN
